README.txt
setup.py
Producer_Consumer/QueueTool.py
Producer_Consumer/__init__.py
Producer_Consumer.egg-info/PKG-INFO
Producer_Consumer.egg-info/SOURCES.txt
Producer_Consumer.egg-info/dependency_links.txt
Producer_Consumer.egg-info/requires.txt
Producer_Consumer.egg-info/top_level.txt