Metadata-Version: 1.0
Name: Producer-Consumer
Version: 19.8
Summary: producer and consumer models
Home-page: https://github.com/lijiacaigit/Producer_Comsumer
Author: Lijiacai
Author-email: 1050518702@qq.com
License: MIT License
Keywords: Queue,queue,Producer_Consumer,producer_consumer,producer,consumer,process
Platform: any
